{"moduleName":null,"summaries":[{"symbol":{"__symbol":0,"members":[]},"metadata":{"__symbolic":"interface"}},{"symbol":{"__symbol":1,"members":[]},"metadata":{"__symbolic":"interface"}},{"symbol":{"__symbol":2,"members":[]},"metadata":{"__symbolic":"interface"}},{"symbol":{"__symbol":3,"members":[]},"metadata":{"__symbolic":"interface"}},{"symbol":{"__symbol":4,"members":[]},"metadata":{"__symbolic":"interface"}}],"symbols":[{"__symbol":0,"name":"IModalDialog","filePath":"./modal-dialog.interface"},{"__symbol":1,"name":"IModalDialogOptions","filePath":"./modal-dialog.interface"},{"__symbol":2,"name":"ModalDialogOnAction","filePath":"./modal-dialog.interface"},{"__symbol":3,"name":"IModalDialogButton","filePath":"./modal-dialog.interface"},{"__symbol":4,"name":"IModalDialogSettings","filePath":"./modal-dialog.interface"}]}